DASP
