Metadata-Version: 1.0
Name: DASP
Version: 0.1.4
Summary: a library for DS CAA Developer
Home-page: https://blog.csdn.net/qq_42197919?spm=1001.2101.3001.5343
Author: Zhimin Wang
Author-email: 934909661@qq.com
License: MIT License
Keywords: ds caa
Platform: any
